mycalc/calculator.py
ysh_calculator-0.0.1.dist-info/LICENSE.txt
ysh_calculator-0.0.1.dist-info/METADATA
ysh_calculator-0.0.1.dist-info/WHEEL
ysh_calculator-0.0.1.dist-info/top_level.txt
ysh_calculator-0.0.1.dist-info/RECORD
