Metadata-Version: 2.1
Name: ysh-calculator
Version: 0.0.1
Summary: nice calculator
Home-page: https://github.com/realp0tato/calc0001
Download-URL: https://github.com/realp0tato/calc0001
Author: yoonshi
Classifier: Programming Language :: Python :: 3
License-File: LICENSE.txt
